labml/__init__.py
labml/app_api.py
labml/cli.py
labml/configs.py
labml/experiment.py
labml/lab.py
labml/logger.py
labml/manage.py
labml/monit.py
labml/tracker.py
labml/internal/__init__.py
labml/internal/lab.py
labml/internal/app/__init__.py
labml/internal/app/configs.py
labml/internal/app/dynamic.py
labml/internal/app/experiment.py
labml/internal/app/logs.py
labml/internal/app/url.py
labml/internal/computer/__init__.py
labml/internal/computer/configs.py
labml/internal/computer/monitoring_process.py
labml/internal/computer/service.py
labml/internal/computer/writer.py
labml/internal/computer/monitor/__init__.py
labml/internal/computer/monitor/process.py
labml/internal/computer/monitor/scanner.py
labml/internal/computer/projects/__init__.py
labml/internal/computer/projects/app.py
labml/internal/computer/projects/methods.py
labml/internal/computer/projects/polling.py
labml/internal/computer/projects/run_summary.py
labml/internal/computer/projects/sync.py
labml/internal/configs/__init__.py
labml/internal/configs/base.py
labml/internal/configs/config_function.py
labml/internal/configs/config_item.py
labml/internal/configs/dynamic_hyperparam.py
labml/internal/configs/eval_function.py
labml/internal/configs/processor.py
labml/internal/configs/utils.py
labml/internal/experiment/__init__.py
labml/internal/experiment/experiment_run.py
labml/internal/experiment/watcher.py
labml/internal/logger/__init__.py
labml/internal/logger/types.py
labml/internal/logger/destinations/__init__.py
labml/internal/logger/destinations/console.py
labml/internal/logger/destinations/factory.py
labml/internal/logger/destinations/ipynb.py
labml/internal/logger/destinations/ipynb_pycharm.py
labml/internal/logger/inspect/__init__.py
labml/internal/manage/__init__.py
labml/internal/manage/process.py
labml/internal/manage/runs.py
labml/internal/monitor/__init__.py
labml/internal/monitor/iterator.py
labml/internal/monitor/loop.py
labml/internal/monitor/mix.py
labml/internal/monitor/sections.py
labml-0.5.3.dist-info/METADATA
labml-0.5.3.dist-info/WHEEL
labml-0.5.3.dist-info/entry_points.txt
labml-0.5.3.dist-info/top_level.txt
labml-0.5.3.dist-info/RECORD
