Metadata-Version: 2.1
Name: labml
Version: 0.5.3
Summary: Organize Machine Learning Experiments
Home-page: https://github.com/labmlai/labml
Author: Varuna Jayasiri, Nipun Wijerathne
Author-email: vpjayasiri@gmail.com, hnipun@gmail.com
Project-URL: Documentation, https://docs.labml.ai/
Keywords: machine learning
Classifier: Programming Language :: Python :: 3
Classifier: License :: OSI Approved :: MIT License
Classifier: Intended Audience :: Developers
Classifier: Intended Audience :: Science/Research
Classifier: Topic :: Scientific/Engineering
Classifier: Topic :: Scientific/Engineering :: Mathematics
Classifier: Topic :: Scientific/Engineering :: Artificial Intelligence
Classifier: Topic :: Software Development
Classifier: Topic :: Software Development :: Libraries
Classifier: Topic :: Software Development :: Libraries :: Python Modules
Requires-Dist: gitpython
Requires-Dist: pyyaml
Requires-Dist: numpy
